<theme>
	<formatVersion>4</formatVersion>

	<view name="system">
		<text name="info1" extra="true">
			<text>MAME significa Multiple Arcade Machine Emulator - Emulador de Múltiplas Máquinas de Arcade, em português. O MAME irá reproduzir, mais ou menos fielmente, o jogo em sua máquina.</text>
		</text>

		
				<text name="info2" extra="true">
			<text>M.A.M.E.</text>
		</text>
		
		<text name="info3" extra="true">
			<text>1997</text>
		</text>
		
		<text name="info4" extra="true">
			<text>Nicola Salmoria</text>
		</text>	

		<text name="info5" extra="true">
			<text>DESENVOLVEDOR:</text>
		</text>
	</view>
</theme>
